pagesnap/__init__.py
pagesnap/pagesnap.py
pagesnap-0.0.2.dist-info/entry_points.txt
pagesnap-0.0.2.dist-info/LICENSE
pagesnap-0.0.2.dist-info/WHEEL
pagesnap-0.0.2.dist-info/METADATA
pagesnap-0.0.2.dist-info/RECORD
