Metadata-Version: 2.1
Name: pagesnap
Version: 0.0.2
Summary: Saving webpage in a single HTML file, based on playwright
Home-page: https://github.com/maxiee/pagesnap
License: MIT
Author: maxiee
Author-email: maxieewong@gmail.com
Requires-Python: >=3.10,<4.0
Classifier: License :: OSI Approved :: MIT License
Classifier: Programming Language :: Python :: 3
Classifier: Programming Language :: Python :: 3.10
Requires-Dist: beautifulsoup4 (>=4.12.2,<5.0.0)
Requires-Dist: playwright (>=1.33.0,<2.0.0)
Project-URL: Repository, https://github.com/maxiee/pagesnap
